subuid/__init__.py
subuid/utils.py
subuid-0.1.1.data/scripts/addsub
subuid-0.1.1.dist-info/METADATA
subuid-0.1.1.dist-info/WHEEL
subuid-0.1.1.dist-info/top_level.txt
subuid-0.1.1.dist-info/RECORD
